quri_parts/stim/NOTICE
quri_parts/stim/__init__.py
quri_parts/stim/circuit/__init__.py
quri_parts/stim/estimator/__init__.py
quri_parts/stim/operator/__init__.py
quri_parts/stim/py.typed
quri_parts/stim/sampler/__init__.py
quri_parts/stim/simulator.py
quri_parts_stim-17.0.0.dist-info/LICENSE
quri_parts_stim-17.0.0.dist-info/METADATA
quri_parts_stim-17.0.0.dist-info/WHEEL
quri_parts_stim-17.0.0.dist-info/RECORD
